plotter/__init__.py
plotter/plotter.py
plotter_cicd-1.0.0a0.dist-info/entry_points.txt
plotter_cicd-1.0.0a0.dist-info/LICENSE
plotter_cicd-1.0.0a0.dist-info/WHEEL
plotter_cicd-1.0.0a0.dist-info/METADATA
plotter_cicd-1.0.0a0.dist-info/RECORD
