Metadata-Version: 2.1
Name: plotter-cicd
Version: 1.0.0a0
Summary: Python template project
Home-page: https://github.com/podaac/poetry-cicd-example
License: Apache-2.0
Author: Frank Greguska
Author-email: 89428916+frankinspace@users.noreply.github.com
Requires-Python: >=3.10,<4.0
Classifier: License :: OSI Approved :: Apache Software License
Classifier: Programming Language :: Python :: 3
Classifier: Programming Language :: Python :: 3.10
Classifier: Topic :: Software Development :: Libraries :: Python Modules
Requires-Dist: matplotlib (>=3.6.2,<4.0.0)
Requires-Dist: numpy (>=1.23.5,<2.0.0)
Project-URL: Repository, https://github.com/podaac/poetry-cicd-example
